LICENSE.txt
README.md
setup.cfg
setup.py
pykea/__init__.py
pykea.egg-info/PKG-INFO
pykea.egg-info/SOURCES.txt
pykea.egg-info/dependency_links.txt
pykea.egg-info/top_level.txt
pykea/vision/__init__.py
pykea/vision/line_finder.py
pykea/vision/omron.py
pykea/waveshare/__init__.py
pykea/waveshare/alphabot.py
pykea/waveshare/pac9685.py
pykea/waveshare/tr_sensor.py