Metadata-Version: 2.1
Name: pykea
Version: 0.7
Summary: Python Package Used By KEA - Copenhagen School of Design and Technology
Home-page: UNKNOWN
Author: Sofian Hanash
Author-email: soha@kea.dk
License: MIT
Keywords: python,beackhoff,ads
Platform: UNKNOWN
Classifier: Programming Language :: Python :: 3
License-File: LICENSE.txt
